{"generated_at": "2026-07-22T09:35:09.263006Z", "source": "ops.pull_ledger + ref.nielsen_delivery_contract", "days_since_pull": 7, "cadence_days": 15, "warn": false, "red": false, "families": [{"dataset_family": "MIT", "pull_cadence_days": 15, "last_pull_ts": "2026-07-16 00:00:00", "days_since": 6, "next_due": "2026-07-31", "notes": "UES_P lags one day behind H sibling \u2014 not a missed delivery"}, {"dataset_family": "WIKIDATA", "pull_cadence_days": 30, "last_pull_ts": "2026-07-17 05:08:19.526743", "days_since": 5, "next_due": "2026-08-16", "notes": "ALTIDS-PRODUCTION-001 B5: monthly delta re-harvest (cron 1st 04:15); CC0; WDQS etiquette per wikidata-fusion skill"}, {"dataset_family": "LAAPP", "pull_cadence_days": 15, "last_pull_ts": "2026-07-15 00:00:00", "days_since": 7, "next_due": "2026-07-30", "notes": "dual generations: BROADCAST_DATE= bulk \u2192 2026-06-16, _date_str= delta 2026-06-17\u2192 (seam dedup S-06)"}, {"dataset_family": "AMRLD", "pull_cadence_days": 15, "last_pull_ts": "2026-07-15 00:00:00", "days_since": 7, "next_due": "2026-07-30", "notes": "Monday batches (REC36/REC71 \u2014 supersedes legacy Wednesday claim, S-02/KB deposit 2026-07-17); due 2026-07-30"}]}
